tesla_ce_provider/__init__.py
tesla_ce_provider/celery_app.py
tesla_ce_provider/data/VERSION
tesla_ce_provider/data/options.json
tesla_ce_provider/message/__init__.py
tesla_ce_provider/message/integrity.py
tesla_ce_provider/message/provider.py
tesla_ce_provider/message/sensor.py
tesla_ce_provider/message/status.py
tesla_ce_provider/models/__init__.py
tesla_ce_provider/models/base.py
tesla_ce_provider/models/fr.py
tesla_ce_provider/models/model.py
tesla_ce_provider/models/parser.py
tesla_ce_provider/provider/__init__.py
tesla_ce_provider/provider/base.py
tesla_ce_provider/provider/result.py
tesla_ce_provider/provider/audit/__init__.py
tesla_ce_provider/provider/audit/base.py
tesla_ce_provider/provider/audit/fr.py
tesla_ce_provider/provider/audit/ks.py
tesla_ce_provider/provider/audit/tp.py
tesla_ce_provider/tasks/__init__.py
tesla_ce_provider/tasks/base.py
tesla_ce_provider/tasks/enrolment.py
tesla_ce_provider/tasks/notification.py
tesla_ce_provider/tasks/verification.py
tesla_ce_provider_fixtures/__init__.py
tesla_ce_provider_fixtures/fixtures.py
tests/__init__.py
tests/conftest.py
tests/base_fixtures/__init__.py
tests/base_fixtures/test_provider_fixtures.py
tesla_ce_provider-0.0.9.dist-info/LICENSE
tesla_ce_provider-0.0.9.dist-info/METADATA
tesla_ce_provider-0.0.9.dist-info/WHEEL
tesla_ce_provider-0.0.9.dist-info/entry_points.txt
tesla_ce_provider-0.0.9.dist-info/top_level.txt
tesla_ce_provider-0.0.9.dist-info/RECORD
