Metadata-Version: 2.1
Name: tesla-ce-provider
Version: 0.0.9
Summary: TeSLA Python SDK for providers
Home-page: https://tesla-ce.github.io
Author: Xavier Baro
Author-email: xbaro@uoc.edu
License: UNKNOWN
Project-URL: Documentation, https://tesla-ce.github.io/python-provider-sdk/
Project-URL: Source, https://github.com/tesla-ce/python-provider-sdk
Platform: UNKNOWN
Classifier: Programming Language :: Python :: 3
Classifier: License :: OSI Approved :: GNU Affero General Public License v3 or later (AGPLv3+)
Classifier: Operating System :: POSIX :: Linux
Classifier: Framework :: Pytest
Requires-Python: >=3.6
License-File: LICENSE
Requires-Dist: celery
Requires-Dist: gevent
Requires-Dist: sentry-sdk
Requires-Dist: simplejson
Requires-Dist: tesla-ce-client (>=0.0.4)
